test/__init__.py
test/api/__init__.py
test/api/sample_spark_chat_client.py
test/api/sample_spark_embedding.py
test/langchain/__init__.py
test/langchain/agents.py
test/langchain/chat_model.py
test/langchain/embed.py
test/langchain/function_call.py
test/langchain/function_call_aiui.py
test/langchain/llm.py
test/langchain/memory.py
test/langchain/retrieval.py
test/langchain/agents/__init__.py
test/langchain/agents/agent_qa.py
test/langchain/agents/ask.py
test/langchain/agents/ask2.py
test/langchain/agents/plan.py
test/langchain/agents/quick_start.py
test/langchain/agents/react.py
test/langchain/agents/slot.py
test/langchain/agents/slot2.py
test/langchain/agents/sparkai_agent.py
test/langchain/agents/tools.py
test/llama_index/__init__.py
test/llama_index/base.py
test/llama_index/indexing.py
test/llama_index/metadata.py
test/llama_index/skydoc-embedding.py
test/llama_index/start.py
test/llama_index/introduce/01_start.py
test/llama_index/introduce/02_reader.py
test/llama_index/introduce/03_custom_file_reader.py
test/llama_index/introduce/04_doc_metadata.py
test/llama_index/introduce/05_splitter.py
test/llama_index/introduce/06_node_metadata.py
test/llama_index/introduce/07_retriever.py
test/llama_index/introduce/07_retriever_custom.py
test/llama_index/introduce/08_postprocessor.py
test/llama_index/introduce/09_prompt.py
test/llama_index/introduce/10_multistep_query_engine.py
test/llama_index/introduce/11_route_query_engine.py
test/llama_index/introduce/12_llamahub.py
test/llama_index/introduce/__init__.py
test/llama_index/introduce/introduce_base.py
test/llama_index/introduce/nltk_demo.py
test/llama_index/optimizing/__init__.py
test/llama_index/optimizing/base.py
test/llama_index/optimizing/custom_keyword_extractor.py
test/llama_index/optimizing/docx_keyword_vector.py
test/llama_index/optimizing/kg_index.py
test/llama_index/optimizing/qa_metadata.py
test/llama_index/optimizing/summary_index.py
test/llama_index/optimizing/summary_metadata.py
turing_planet-0.1.4.dist-info/METADATA
turing_planet-0.1.4.dist-info/WHEEL
turing_planet-0.1.4.dist-info/top_level.txt
turing_planet-0.1.4.dist-info/RECORD
