Metadata-Version: 2.1
Name: turing-planet
Version: 0.1.4
Summary: Python Extension Framework For Turing Planet
Home-page: https://code.iflytek.com/osc/_source/Y_RDG-TURING/gpt/turing-planet/-/tree/heads%2Fdevelop
Author: jianwu6
Author-email: jianwu6@iflytek.com
Classifier: Programming Language :: Python :: 3
Classifier: License :: OSI Approved :: MIT License
Classifier: Operating System :: OS Independent
Requires-Python: >=3.9.0, <3.10.0
Requires-Dist: langchain ==0.1.0
Requires-Dist: llama-index ==0.10.0
Requires-Dist: websocket-client ==1.6.4
